asfpy/__init__.py
asfpy/asfpy.py
asfpy_phd-0.6.1.dist-info/LICENSE
asfpy_phd-0.6.1.dist-info/METADATA
asfpy_phd-0.6.1.dist-info/WHEEL
asfpy_phd-0.6.1.dist-info/top_level.txt
asfpy_phd-0.6.1.dist-info/RECORD
